{
  "$schema": "https://json-schema.org/draft/2020-12/schema",
  "$id": "https://www.rethinkhealth.io/hl7v2/CSU_C09.schema.json",
  "title": "HL7v2 CSU_C09",
  "type": "object",
  "description": "JSON Schema definition for HL7v2",
  "properties": {
    "MSH": {
      "type": "object",
      "metadata": {
        "minOccurs": "1",
        "maxOccurs": "1",
        "optionality": "Required",
        "repeatability": "Unique"
      }
    },
    "SFT": {
      "type": "object",
      "metadata": {
        "minOccurs": "0",
        "maxOccurs": "unbounded",
        "optionality": "Optional",
        "repeatability": "Multiple"
      }
    },
    "UAC": {
      "type": "object",
      "metadata": {
        "minOccurs": "0",
        "maxOccurs": "1",
        "optionality": "Optional",
        "repeatability": "Unique"
      }
    },
    "PATIENT": {
      "$ref": "/schemas/PATIENT",
      "metadata": {
        "minOccurs": "1",
        "maxOccurs": "unbounded",
        "optionality": "Required",
        "repeatability": "Multiple"
      }
    }
  },
  "required": [
    "MSH",
    "PATIENT"
  ],
  "$defs": {
    "PATIENT": {
      "$id": "/schemas/PATIENT",
      "$schema": "http://json-schema.org/draft-07/schema#",
      "type": "object",
      "properties": {
        "PID": {
          "type": "object",
          "metadata": {
            "minOccurs": "1",
            "maxOccurs": "1",
            "optionality": "Required",
            "repeatability": "Unique"
          }
        },
        "PD1": {
          "type": "object",
          "metadata": {
            "minOccurs": "0",
            "maxOccurs": "1",
            "optionality": "Optional",
            "repeatability": "Unique"
          }
        },
        "PRT": {
          "type": "object",
          "metadata": {
            "minOccurs": "0",
            "maxOccurs": "unbounded",
            "optionality": "Optional",
            "repeatability": "Multiple"
          }
        },
        "ARV": {
          "type": "object",
          "metadata": {
            "minOccurs": "0",
            "maxOccurs": "unbounded",
            "optionality": "Optional",
            "repeatability": "Multiple"
          }
        },
        "NTE": {
          "type": "object",
          "metadata": {
            "minOccurs": "0",
            "maxOccurs": "unbounded",
            "optionality": "Optional",
            "repeatability": "Multiple"
          }
        },
        "VISIT": {
          "$ref": "/schemas/VISIT",
          "metadata": {
            "minOccurs": "0",
            "maxOccurs": "1",
            "optionality": "Optional",
            "repeatability": "Unique"
          }
        },
        "CSR": {
          "type": "object",
          "metadata": {
            "minOccurs": "1",
            "maxOccurs": "1",
            "optionality": "Required",
            "repeatability": "Unique"
          }
        },
        "STUDY_PHASE": {
          "$ref": "/schemas/STUDY_PHASE",
          "metadata": {
            "minOccurs": "1",
            "maxOccurs": "unbounded",
            "optionality": "Required",
            "repeatability": "Multiple"
          }
        }
      },
      "required": [
        "PID",
        "CSR",
        "STUDY_PHASE"
      ]
    },
    "VISIT": {
      "$id": "/schemas/VISIT",
      "$schema": "http://json-schema.org/draft-07/schema#",
      "type": "object",
      "properties": {
        "PV1": {
          "type": "object",
          "metadata": {
            "minOccurs": "1",
            "maxOccurs": "1",
            "optionality": "Required",
            "repeatability": "Unique"
          }
        },
        "PV2": {
          "type": "object",
          "metadata": {
            "minOccurs": "0",
            "maxOccurs": "1",
            "optionality": "Optional",
            "repeatability": "Unique"
          }
        },
        "PRT": {
          "type": "object",
          "metadata": {
            "minOccurs": "0",
            "maxOccurs": "unbounded",
            "optionality": "Optional",
            "repeatability": "Multiple"
          }
        }
      },
      "required": [
        "PV1"
      ]
    },
    "STUDY_PHASE": {
      "$id": "/schemas/STUDY_PHASE",
      "$schema": "http://json-schema.org/draft-07/schema#",
      "type": "object",
      "properties": {
        "CSP": {
          "type": "object",
          "metadata": {
            "minOccurs": "0",
            "maxOccurs": "1",
            "optionality": "Optional",
            "repeatability": "Unique"
          }
        },
        "STUDY_SCHEDULE": {
          "$ref": "/schemas/STUDY_SCHEDULE",
          "metadata": {
            "minOccurs": "1",
            "maxOccurs": "unbounded",
            "optionality": "Required",
            "repeatability": "Multiple"
          }
        }
      },
      "required": [
        "STUDY_SCHEDULE"
      ]
    },
    "STUDY_SCHEDULE": {
      "$id": "/schemas/STUDY_SCHEDULE",
      "$schema": "http://json-schema.org/draft-07/schema#",
      "type": "object",
      "properties": {
        "CSS": {
          "type": "object",
          "metadata": {
            "minOccurs": "0",
            "maxOccurs": "1",
            "optionality": "Optional",
            "repeatability": "Unique"
          }
        },
        "STUDY_OBSERVATION": {
          "$ref": "/schemas/STUDY_OBSERVATION",
          "metadata": {
            "minOccurs": "1",
            "maxOccurs": "unbounded",
            "optionality": "Required",
            "repeatability": "Multiple"
          }
        },
        "STUDY_PHARM": {
          "$ref": "/schemas/STUDY_PHARM",
          "metadata": {
            "minOccurs": "1",
            "maxOccurs": "unbounded",
            "optionality": "Required",
            "repeatability": "Multiple"
          }
        }
      },
      "required": [
        "STUDY_OBSERVATION",
        "STUDY_PHARM"
      ]
    },
    "STUDY_OBSERVATION": {
      "$id": "/schemas/STUDY_OBSERVATION",
      "$schema": "http://json-schema.org/draft-07/schema#",
      "type": "object",
      "properties": {
        "STUDY_OBSERVATION_ORDER": {
          "$ref": "/schemas/STUDY_OBSERVATION_ORDER",
          "metadata": {
            "minOccurs": "0",
            "maxOccurs": "1",
            "optionality": "Optional",
            "repeatability": "Unique"
          }
        },
        "OBR": {
          "type": "object",
          "metadata": {
            "minOccurs": "1",
            "maxOccurs": "1",
            "optionality": "Required",
            "repeatability": "Unique"
          }
        },
        "PRT": {
          "type": "object",
          "metadata": {
            "minOccurs": [
              "0",
              "0"
            ],
            "maxOccurs": [
              "unbounded",
              "unbounded"
            ],
            "optionality": "Required",
            "repeatability": "Multiple"
          }
        },
        "TIMING_QTY": {
          "$ref": "/schemas/TIMING_QTY",
          "metadata": {
            "minOccurs": "0",
            "maxOccurs": "unbounded",
            "optionality": "Optional",
            "repeatability": "Multiple"
          }
        },
        "OBX": {
          "type": "object",
          "metadata": {
            "minOccurs": "1",
            "maxOccurs": "1",
            "optionality": "Required",
            "repeatability": "Unique"
          }
        }
      },
      "required": [
        "OBR",
        "OBX"
      ]
    },
    "STUDY_OBSERVATION_ORDER": {
      "$id": "/schemas/STUDY_OBSERVATION_ORDER",
      "$schema": "http://json-schema.org/draft-07/schema#",
      "type": "object",
      "properties": {
        "ORC": {
          "type": "object",
          "metadata": {
            "minOccurs": "1",
            "maxOccurs": "1",
            "optionality": "Required",
            "repeatability": "Unique"
          }
        },
        "PRT": {
          "type": "object",
          "metadata": {
            "minOccurs": "0",
            "maxOccurs": "unbounded",
            "optionality": "Optional",
            "repeatability": "Multiple"
          }
        }
      },
      "required": [
        "ORC"
      ]
    },
    "TIMING_QTY": {
      "$id": "/schemas/TIMING_QTY",
      "$schema": "http://json-schema.org/draft-07/schema#",
      "type": "object",
      "properties": {
        "TQ1": {
          "type": "object",
          "metadata": {
            "minOccurs": "1",
            "maxOccurs": "1",
            "optionality": "Required",
            "repeatability": "Unique"
          }
        },
        "TQ2": {
          "type": "object",
          "metadata": {
            "minOccurs": "0",
            "maxOccurs": "unbounded",
            "optionality": "Optional",
            "repeatability": "Multiple"
          }
        }
      },
      "required": [
        "TQ1"
      ]
    },
    "STUDY_PHARM": {
      "$id": "/schemas/STUDY_PHARM",
      "$schema": "http://json-schema.org/draft-07/schema#",
      "type": "object",
      "properties": {
        "COMMON_ORDER": {
          "$ref": "/schemas/COMMON_ORDER",
          "metadata": {
            "minOccurs": "0",
            "maxOccurs": "1",
            "optionality": "Optional",
            "repeatability": "Unique"
          }
        },
        "RX_ADMIN": {
          "$ref": "/schemas/RX_ADMIN",
          "metadata": {
            "minOccurs": "1",
            "maxOccurs": "unbounded",
            "optionality": "Required",
            "repeatability": "Multiple"
          }
        }
      },
      "required": [
        "RX_ADMIN"
      ]
    },
    "COMMON_ORDER": {
      "$id": "/schemas/COMMON_ORDER",
      "$schema": "http://json-schema.org/draft-07/schema#",
      "type": "object",
      "properties": {
        "ORC": {
          "type": "object",
          "metadata": {
            "minOccurs": "1",
            "maxOccurs": "1",
            "optionality": "Required",
            "repeatability": "Unique"
          }
        },
        "PRT": {
          "type": "object",
          "metadata": {
            "minOccurs": "0",
            "maxOccurs": "unbounded",
            "optionality": "Optional",
            "repeatability": "Multiple"
          }
        }
      },
      "required": [
        "ORC"
      ]
    },
    "RX_ADMIN": {
      "$id": "/schemas/RX_ADMIN",
      "$schema": "http://json-schema.org/draft-07/schema#",
      "type": "object",
      "properties": {
        "RXA": {
          "type": "object",
          "metadata": {
            "minOccurs": "1",
            "maxOccurs": "1",
            "optionality": "Required",
            "repeatability": "Unique"
          }
        },
        "RXR": {
          "type": "object",
          "metadata": {
            "minOccurs": "1",
            "maxOccurs": "1",
            "optionality": "Required",
            "repeatability": "Unique"
          }
        },
        "PRT": {
          "type": "object",
          "metadata": {
            "minOccurs": "0",
            "maxOccurs": "unbounded",
            "optionality": "Optional",
            "repeatability": "Multiple"
          }
        }
      },
      "required": [
        "RXA",
        "RXR"
      ]
    }
  }
}