{
  "$schema": "https://json-schema.org/draft/2020-12/schema",
  "$id": "https://www.rethinkhealth.io/hl7v2/RDR_RDR.schema.json",
  "title": "HL7v2 RDR_RDR",
  "type": "object",
  "description": "JSON Schema definition for HL7v2",
  "properties": {
    "MSH": {
      "type": "object",
      "metadata": {
        "minOccurs": "1",
        "maxOccurs": "1",
        "optionality": "Required",
        "repeatability": "Unique"
      }
    },
    "MSA": {
      "type": "object",
      "metadata": {
        "minOccurs": "1",
        "maxOccurs": "1",
        "optionality": "Required",
        "repeatability": "Unique"
      }
    },
    "ERR": {
      "type": "object",
      "metadata": {
        "minOccurs": "0",
        "maxOccurs": "unbounded",
        "optionality": "Optional",
        "repeatability": "Multiple"
      }
    },
    "SFT": {
      "type": "object",
      "metadata": {
        "minOccurs": "0",
        "maxOccurs": "1",
        "optionality": "Optional",
        "repeatability": "Unique"
      }
    },
    "UAC": {
      "type": "object",
      "metadata": {
        "minOccurs": "0",
        "maxOccurs": "1",
        "optionality": "Optional",
        "repeatability": "Unique"
      }
    },
    "DEFINITION": {
      "$ref": "/schemas/DEFINITION",
      "metadata": {
        "minOccurs": "1",
        "maxOccurs": "unbounded",
        "optionality": "Required",
        "repeatability": "Multiple"
      }
    },
    "DSC": {
      "type": "object",
      "metadata": {
        "minOccurs": "0",
        "maxOccurs": "1",
        "optionality": "Optional",
        "repeatability": "Unique"
      }
    }
  },
  "required": [
    "MSH",
    "MSA",
    "DEFINITION"
  ],
  "$defs": {
    "DEFINITION": {
      "$id": "/schemas/DEFINITION",
      "$schema": "http://json-schema.org/draft-07/schema#",
      "type": "object",
      "properties": {
        "QRD": {
          "type": "object",
          "metadata": {
            "minOccurs": "1",
            "maxOccurs": "1",
            "optionality": "Required",
            "repeatability": "Unique"
          }
        },
        "QRF": {
          "type": "object",
          "metadata": {
            "minOccurs": "0",
            "maxOccurs": "1",
            "optionality": "Optional",
            "repeatability": "Unique"
          }
        },
        "PATIENT": {
          "$ref": "/schemas/PATIENT",
          "metadata": {
            "minOccurs": "0",
            "maxOccurs": "1",
            "optionality": "Optional",
            "repeatability": "Unique"
          }
        },
        "ORDER": {
          "$ref": "/schemas/ORDER",
          "metadata": {
            "minOccurs": "1",
            "maxOccurs": "unbounded",
            "optionality": "Required",
            "repeatability": "Multiple"
          }
        }
      },
      "required": [
        "QRD",
        "ORDER"
      ]
    },
    "PATIENT": {
      "$id": "/schemas/PATIENT",
      "$schema": "http://json-schema.org/draft-07/schema#",
      "type": "object",
      "properties": {
        "PID": {
          "type": "object",
          "metadata": {
            "minOccurs": "1",
            "maxOccurs": "1",
            "optionality": "Required",
            "repeatability": "Unique"
          }
        },
        "NTE": {
          "type": "object",
          "metadata": {
            "minOccurs": "0",
            "maxOccurs": "unbounded",
            "optionality": "Optional",
            "repeatability": "Multiple"
          }
        }
      },
      "required": [
        "PID"
      ]
    },
    "ORDER": {
      "$id": "/schemas/ORDER",
      "$schema": "http://json-schema.org/draft-07/schema#",
      "type": "object",
      "properties": {
        "ORC": {
          "type": "object",
          "metadata": {
            "minOccurs": "1",
            "maxOccurs": "1",
            "optionality": "Required",
            "repeatability": "Unique"
          }
        },
        "TIMING": {
          "$ref": "/schemas/TIMING",
          "metadata": {
            "minOccurs": "0",
            "maxOccurs": "unbounded",
            "optionality": "Optional",
            "repeatability": "Multiple"
          }
        },
        "ENCODING": {
          "$ref": "/schemas/ENCODING",
          "metadata": {
            "minOccurs": "0",
            "maxOccurs": "1",
            "optionality": "Optional",
            "repeatability": "Unique"
          }
        },
        "DISPENSE": {
          "$ref": "/schemas/DISPENSE",
          "metadata": {
            "minOccurs": "1",
            "maxOccurs": "unbounded",
            "optionality": "Required",
            "repeatability": "Multiple"
          }
        }
      },
      "required": [
        "ORC",
        "DISPENSE"
      ]
    },
    "TIMING": {
      "$id": "/schemas/TIMING",
      "$schema": "http://json-schema.org/draft-07/schema#",
      "type": "object",
      "properties": {
        "TQ1": {
          "type": "object",
          "metadata": {
            "minOccurs": "1",
            "maxOccurs": "1",
            "optionality": "Required",
            "repeatability": "Unique"
          }
        },
        "TQ2": {
          "type": "object",
          "metadata": {
            "minOccurs": "0",
            "maxOccurs": "unbounded",
            "optionality": "Optional",
            "repeatability": "Multiple"
          }
        }
      },
      "required": [
        "TQ1"
      ]
    },
    "ENCODING": {
      "$id": "/schemas/ENCODING",
      "$schema": "http://json-schema.org/draft-07/schema#",
      "type": "object",
      "properties": {
        "RXE": {
          "type": "object",
          "metadata": {
            "minOccurs": "1",
            "maxOccurs": "1",
            "optionality": "Required",
            "repeatability": "Unique"
          }
        },
        "TIMING_ENCODED": {
          "$ref": "/schemas/TIMING_ENCODED",
          "metadata": {
            "minOccurs": "0",
            "maxOccurs": "unbounded",
            "optionality": "Optional",
            "repeatability": "Multiple"
          }
        },
        "RXR": {
          "type": "object",
          "metadata": {
            "minOccurs": "1",
            "maxOccurs": "unbounded",
            "optionality": "Required",
            "repeatability": "Multiple"
          }
        },
        "RXC": {
          "type": "object",
          "metadata": {
            "minOccurs": "0",
            "maxOccurs": "unbounded",
            "optionality": "Optional",
            "repeatability": "Multiple"
          }
        }
      },
      "required": [
        "RXE",
        "RXR"
      ]
    },
    "TIMING_ENCODED": {
      "$id": "/schemas/TIMING_ENCODED",
      "$schema": "http://json-schema.org/draft-07/schema#",
      "type": "object",
      "properties": {
        "TQ1": {
          "type": "object",
          "metadata": {
            "minOccurs": "1",
            "maxOccurs": "1",
            "optionality": "Required",
            "repeatability": "Unique"
          }
        },
        "TQ2": {
          "type": "object",
          "metadata": {
            "minOccurs": "0",
            "maxOccurs": "unbounded",
            "optionality": "Optional",
            "repeatability": "Multiple"
          }
        }
      },
      "required": [
        "TQ1"
      ]
    },
    "DISPENSE": {
      "$id": "/schemas/DISPENSE",
      "$schema": "http://json-schema.org/draft-07/schema#",
      "type": "object",
      "properties": {
        "RXD": {
          "type": "object",
          "metadata": {
            "minOccurs": "1",
            "maxOccurs": "1",
            "optionality": "Required",
            "repeatability": "Unique"
          }
        },
        "RXR": {
          "type": "object",
          "metadata": {
            "minOccurs": "1",
            "maxOccurs": "unbounded",
            "optionality": "Required",
            "repeatability": "Multiple"
          }
        },
        "RXC": {
          "type": "object",
          "metadata": {
            "minOccurs": "0",
            "maxOccurs": "unbounded",
            "optionality": "Optional",
            "repeatability": "Multiple"
          }
        }
      },
      "required": [
        "RXD",
        "RXR"
      ]
    }
  }
}