{"$id":"https://www.rethinkhealth.io/schemas/PMU_B04.schema.json","$schema":"https://json-schema.org/draft/2020-12/schema","description":"JSON Schema definition for HL7v2","properties":{"EVN":{"$ref":"segments.schema.json#/definitions/EVN","metadata":{"maxOccurs":"1","minOccurs":"1","optionality":"Required","repeatability":"Unique"}},"MSH":{"$ref":"segments.schema.json#/definitions/MSH","metadata":{"maxOccurs":"1","minOccurs":"1","optionality":"Required","repeatability":"Unique"}},"ORG":{"anyOf":[{"$ref":"segments.schema.json#/definitions/ORG"},{"items":{"$ref":"segments.schema.json#/definitions/ORG"},"type":"array"}],"metadata":{"maxOccurs":"unbounded","minOccurs":"0","optionality":"Optional","repeatability":"Multiple"}},"PRA":{"anyOf":[{"$ref":"segments.schema.json#/definitions/PRA"},{"items":{"$ref":"segments.schema.json#/definitions/PRA"},"type":"array"}],"metadata":{"maxOccurs":"unbounded","minOccurs":"0","optionality":"Optional","repeatability":"Multiple"}},"SFT":{"anyOf":[{"$ref":"segments.schema.json#/definitions/SFT"},{"items":{"$ref":"segments.schema.json#/definitions/SFT"},"type":"array"}],"metadata":{"maxOccurs":"unbounded","minOccurs":"0","optionality":"Optional","repeatability":"Multiple"}},"STF":{"$ref":"segments.schema.json#/definitions/STF","metadata":{"maxOccurs":"1","minOccurs":"1","optionality":"Required","repeatability":"Unique"}}},"required":["MSH","EVN","STF"],"title":"HL7v2 PMU_B04","type":"object"}