{"$defs":{"COMPONENTS":{"$id":"/schemas/COMPONENTS","$schema":"http://json-schema.org/draft-07/schema#","properties":{"NTE":{"anyOf":[{"$ref":"segments.schema.json#/definitions/NTE"},{"items":{"$ref":"segments.schema.json#/definitions/NTE"},"type":"array"}],"metadata":{"maxOccurs":"unbounded","minOccurs":"0","optionality":"Optional","repeatability":"Multiple"}},"RXC":{"$ref":"segments.schema.json#/definitions/RXC","metadata":{"maxOccurs":"1","minOccurs":"1","optionality":"Required","repeatability":"Unique"}}},"required":["RXC"],"type":"object"},"ENCODING":{"$id":"/schemas/ENCODING","$schema":"http://json-schema.org/draft-07/schema#","properties":{"RXC":{"anyOf":[{"$ref":"segments.schema.json#/definitions/RXC"},{"items":{"$ref":"segments.schema.json#/definitions/RXC"},"type":"array"}],"metadata":{"maxOccurs":"unbounded","minOccurs":"0","optionality":"Optional","repeatability":"Multiple"}},"RXE":{"$ref":"segments.schema.json#/definitions/RXE","metadata":{"maxOccurs":"1","minOccurs":"1","optionality":"Required","repeatability":"Unique"}},"RXR":{"anyOf":[{"$ref":"segments.schema.json#/definitions/RXR"},{"items":{"$ref":"segments.schema.json#/definitions/RXR"},"type":"array"}],"metadata":{"maxOccurs":"unbounded","minOccurs":"1","optionality":"Required","repeatability":"Multiple"}},"TIMING_ENCODED":{"anyOf":[{"$ref":"/schemas/TIMING_ENCODED"},{"items":{"$ref":"/schemas/TIMING_ENCODED"},"type":"array"}],"metadata":{"maxOccurs":"unbounded","minOccurs":"1","optionality":"Required","repeatability":"Multiple"}}},"required":["RXE","TIMING_ENCODED","RXR"],"type":"object"},"GIVE":{"$id":"/schemas/GIVE","$schema":"http://json-schema.org/draft-07/schema#","properties":{"OBSERVATION":{"anyOf":[{"$ref":"/schemas/OBSERVATION"},{"items":{"$ref":"/schemas/OBSERVATION"},"type":"array"}],"metadata":{"maxOccurs":"unbounded","minOccurs":"1","optionality":"Required","repeatability":"Multiple"}},"RXC":{"anyOf":[{"$ref":"segments.schema.json#/definitions/RXC"},{"items":{"$ref":"segments.schema.json#/definitions/RXC"},"type":"array"}],"metadata":{"maxOccurs":"unbounded","minOccurs":"0","optionality":"Optional","repeatability":"Multiple"}},"RXG":{"$ref":"segments.schema.json#/definitions/RXG","metadata":{"maxOccurs":"1","minOccurs":"1","optionality":"Required","repeatability":"Unique"}},"RXR":{"anyOf":[{"$ref":"segments.schema.json#/definitions/RXR"},{"items":{"$ref":"segments.schema.json#/definitions/RXR"},"type":"array"}],"metadata":{"maxOccurs":"unbounded","minOccurs":"1","optionality":"Required","repeatability":"Multiple"}},"TIMING_GIVE":{"anyOf":[{"$ref":"/schemas/TIMING_GIVE"},{"items":{"$ref":"/schemas/TIMING_GIVE"},"type":"array"}],"metadata":{"maxOccurs":"unbounded","minOccurs":"1","optionality":"Required","repeatability":"Multiple"}}},"required":["RXG","TIMING_GIVE","RXR","OBSERVATION"],"type":"object"},"OBSERVATION":{"$id":"/schemas/OBSERVATION","$schema":"http://json-schema.org/draft-07/schema#","properties":{"NTE":{"anyOf":[{"$ref":"segments.schema.json#/definitions/NTE"},{"items":{"$ref":"segments.schema.json#/definitions/NTE"},"type":"array"}],"metadata":{"maxOccurs":"unbounded","minOccurs":"0","optionality":"Optional","repeatability":"Multiple"}},"OBX":{"$ref":"segments.schema.json#/definitions/OBX","metadata":{"maxOccurs":"1","minOccurs":"0","optionality":"Optional","repeatability":"Unique"}}},"required":[],"type":"object"},"ORDER":{"$id":"/schemas/ORDER","$schema":"http://json-schema.org/draft-07/schema#","properties":{"ENCODING":{"$ref":"/schemas/ENCODING","metadata":{"maxOccurs":"1","minOccurs":"0","optionality":"Optional","repeatability":"Unique"}},"GIVE":{"anyOf":[{"$ref":"/schemas/GIVE"},{"items":{"$ref":"/schemas/GIVE"},"type":"array"}],"metadata":{"maxOccurs":"unbounded","minOccurs":"1","optionality":"Required","repeatability":"Multiple"}},"ORC":{"$ref":"segments.schema.json#/definitions/ORC","metadata":{"maxOccurs":"1","minOccurs":"1","optionality":"Required","repeatability":"Unique"}},"ORDER_DETAIL":{"$ref":"/schemas/ORDER_DETAIL","metadata":{"maxOccurs":"1","minOccurs":"0","optionality":"Optional","repeatability":"Unique"}},"TIMING":{"anyOf":[{"$ref":"/schemas/TIMING"},{"items":{"$ref":"/schemas/TIMING"},"type":"array"}],"metadata":{"maxOccurs":"unbounded","minOccurs":"0","optionality":"Optional","repeatability":"Multiple"}}},"required":["ORC","GIVE"],"type":"object"},"ORDER_DETAIL":{"$id":"/schemas/ORDER_DETAIL","$schema":"http://json-schema.org/draft-07/schema#","properties":{"ORDER_DETAIL_SUPPLEMENT":{"$ref":"/schemas/ORDER_DETAIL_SUPPLEMENT","metadata":{"maxOccurs":"1","minOccurs":"0","optionality":"Optional","repeatability":"Unique"}},"RXO":{"$ref":"segments.schema.json#/definitions/RXO","metadata":{"maxOccurs":"1","minOccurs":"1","optionality":"Required","repeatability":"Unique"}}},"required":["RXO"],"type":"object"},"ORDER_DETAIL_SUPPLEMENT":{"$id":"/schemas/ORDER_DETAIL_SUPPLEMENT","$schema":"http://json-schema.org/draft-07/schema#","properties":{"COMPONENTS":{"anyOf":[{"$ref":"/schemas/COMPONENTS"},{"items":{"$ref":"/schemas/COMPONENTS"},"type":"array"}],"metadata":{"maxOccurs":"unbounded","minOccurs":"0","optionality":"Optional","repeatability":"Multiple"}},"NTE":{"anyOf":[{"$ref":"segments.schema.json#/definitions/NTE"},{"items":{"$ref":"segments.schema.json#/definitions/NTE"},"type":"array"}],"metadata":{"maxOccurs":"unbounded","minOccurs":"1","optionality":"Required","repeatability":"Multiple"}},"RXR":{"anyOf":[{"$ref":"segments.schema.json#/definitions/RXR"},{"items":{"$ref":"segments.schema.json#/definitions/RXR"},"type":"array"}],"metadata":{"maxOccurs":"unbounded","minOccurs":"1","optionality":"Required","repeatability":"Multiple"}}},"required":["NTE","RXR"],"type":"object"},"PATIENT":{"$id":"/schemas/PATIENT","$schema":"http://json-schema.org/draft-07/schema#","properties":{"AL1":{"anyOf":[{"$ref":"segments.schema.json#/definitions/AL1"},{"items":{"$ref":"segments.schema.json#/definitions/AL1"},"type":"array"}],"metadata":{"maxOccurs":"unbounded","minOccurs":"0","optionality":"Optional","repeatability":"Multiple"}},"NTE":{"anyOf":[{"$ref":"segments.schema.json#/definitions/NTE"},{"items":{"$ref":"segments.schema.json#/definitions/NTE"},"type":"array"}],"metadata":{"maxOccurs":"unbounded","minOccurs":"0","optionality":"Optional","repeatability":"Multiple"}},"PATIENT_VISIT":{"$ref":"/schemas/PATIENT_VISIT","metadata":{"maxOccurs":"1","minOccurs":"0","optionality":"Optional","repeatability":"Unique"}},"PID":{"$ref":"segments.schema.json#/definitions/PID","metadata":{"maxOccurs":"1","minOccurs":"1","optionality":"Required","repeatability":"Unique"}}},"required":["PID"],"type":"object"},"PATIENT_VISIT":{"$id":"/schemas/PATIENT_VISIT","$schema":"http://json-schema.org/draft-07/schema#","properties":{"PV1":{"$ref":"segments.schema.json#/definitions/PV1","metadata":{"maxOccurs":"1","minOccurs":"1","optionality":"Required","repeatability":"Unique"}},"PV2":{"$ref":"segments.schema.json#/definitions/PV2","metadata":{"maxOccurs":"1","minOccurs":"0","optionality":"Optional","repeatability":"Unique"}}},"required":["PV1"],"type":"object"},"TIMING":{"$id":"/schemas/TIMING","$schema":"http://json-schema.org/draft-07/schema#","properties":{"TQ1":{"$ref":"segments.schema.json#/definitions/TQ1","metadata":{"maxOccurs":"1","minOccurs":"1","optionality":"Required","repeatability":"Unique"}},"TQ2":{"anyOf":[{"$ref":"segments.schema.json#/definitions/TQ2"},{"items":{"$ref":"segments.schema.json#/definitions/TQ2"},"type":"array"}],"metadata":{"maxOccurs":"unbounded","minOccurs":"0","optionality":"Optional","repeatability":"Multiple"}}},"required":["TQ1"],"type":"object"},"TIMING_ENCODED":{"$id":"/schemas/TIMING_ENCODED","$schema":"http://json-schema.org/draft-07/schema#","properties":{"TQ1":{"$ref":"segments.schema.json#/definitions/TQ1","metadata":{"maxOccurs":"1","minOccurs":"1","optionality":"Required","repeatability":"Unique"}},"TQ2":{"anyOf":[{"$ref":"segments.schema.json#/definitions/TQ2"},{"items":{"$ref":"segments.schema.json#/definitions/TQ2"},"type":"array"}],"metadata":{"maxOccurs":"unbounded","minOccurs":"0","optionality":"Optional","repeatability":"Multiple"}}},"required":["TQ1"],"type":"object"},"TIMING_GIVE":{"$id":"/schemas/TIMING_GIVE","$schema":"http://json-schema.org/draft-07/schema#","properties":{"TQ1":{"$ref":"segments.schema.json#/definitions/TQ1","metadata":{"maxOccurs":"1","minOccurs":"1","optionality":"Required","repeatability":"Unique"}},"TQ2":{"anyOf":[{"$ref":"segments.schema.json#/definitions/TQ2"},{"items":{"$ref":"segments.schema.json#/definitions/TQ2"},"type":"array"}],"metadata":{"maxOccurs":"unbounded","minOccurs":"0","optionality":"Optional","repeatability":"Multiple"}}},"required":["TQ1"],"type":"object"}},"$id":"https://www.rethinkhealth.io/schemas/RGV_O15.schema.json","$schema":"https://json-schema.org/draft/2020-12/schema","description":"JSON Schema definition for HL7v2","properties":{"MSH":{"$ref":"segments.schema.json#/definitions/MSH","metadata":{"maxOccurs":"1","minOccurs":"1","optionality":"Required","repeatability":"Unique"}},"NTE":{"anyOf":[{"$ref":"segments.schema.json#/definitions/NTE"},{"items":{"$ref":"segments.schema.json#/definitions/NTE"},"type":"array"}],"metadata":{"maxOccurs":"unbounded","minOccurs":"0","optionality":"Optional","repeatability":"Multiple"}},"ORDER":{"anyOf":[{"$ref":"/schemas/ORDER"},{"items":{"$ref":"/schemas/ORDER"},"type":"array"}],"metadata":{"maxOccurs":"unbounded","minOccurs":"1","optionality":"Required","repeatability":"Multiple"}},"PATIENT":{"$ref":"/schemas/PATIENT","metadata":{"maxOccurs":"1","minOccurs":"0","optionality":"Optional","repeatability":"Unique"}},"SFT":{"anyOf":[{"$ref":"segments.schema.json#/definitions/SFT"},{"items":{"$ref":"segments.schema.json#/definitions/SFT"},"type":"array"}],"metadata":{"maxOccurs":"unbounded","minOccurs":"0","optionality":"Optional","repeatability":"Multiple"}}},"required":["MSH","ORDER"],"title":"HL7v2 RGV_O15","type":"object"}